setup.py
ljf7/__init__.py
ljf7/email.py
ljf7/fib.py
ljf7_email.egg-info/PKG-INFO
ljf7_email.egg-info/SOURCES.txt
ljf7_email.egg-info/dependency_links.txt
ljf7_email.egg-info/top_level.txt