Metadata-Version: 2.1
Name: ljf7-email
Version: 101
Summary: To solve fib by recursion
Author: Linus Trovalds
